apps/__init__.py
apps/carbon_footprint.py
apps/data_visualization.py
apps/eco_tips.py
apps/menu.py
apps/admin/__init__.py
apps/admin/admin_panel.py
apps/challenges/__init__.py
apps/challenges/eco_challenges.py
apps/dashboard/__init__.py
apps/dashboard/dashboard.py
apps/data_viz/__init__.py
apps/data_viz/activity_summary.py
apps/data_viz/base.py
apps/data_viz/carbon_savings.py
apps/data_viz/data_exporter.py
apps/data_viz/progress_tracker.py
apps/data_viz/report_generator.py
apps/data_viz/trip_history.py
apps/data_viz/ui_utilities.py
apps/data_viz/visualization_manager.py
apps/developer/__init__.py
apps/developer/backup_manager.py
apps/developer/developer_coordinator.py
apps/developer/developer_coordinator_minimal.py
apps/developer/developer_tools.py
apps/developer/developer_ui.py
apps/developer/ui/__init__.py
apps/developer/ui/api_testing_ui.py
apps/developer/ui/backup_restore_ui.py
apps/developer/ui/base_ui.py
apps/developer/ui/cache_management_ui.py
apps/developer/ui/configuration_ui.py
apps/developer/ui/data_management_ui.py
apps/developer/ui/display_utils.py
apps/developer/ui/email_testing_ui.py
apps/developer/ui/export_management_ui.py
apps/developer/ui/health_dashboard_ui.py
apps/developer/ui/log_analysis_ui.py
apps/developer/ui/performance_monitoring_ui.py
apps/developer/ui/security_audit_ui.py
apps/developer/ui/session_management_ui.py
apps/developer/ui/system_monitoring_ui.py
apps/developer/ui/system_repair_ui.py
apps/gamification/__init__.py
apps/gamification/social_gamification.py
apps/route_planner/__init__.py
apps/route_planner/ai_route_planner.py
apps/route_planner/weather_route_planner.py
apps/route_planner/ai_planner/__init__.py
apps/route_planner/ai_planner/planner.py
apps/route_planner/ai_planner/api/__init__.py
apps/route_planner/ai_planner/api/gemini_api.py
apps/route_planner/ai_planner/models/__init__.py
apps/route_planner/ai_planner/models/route.py
apps/route_planner/ai_planner/ui/__init__.py
apps/route_planner/ai_planner/ui/cli.py
ecocycle-3.4.0.dist-info/licenses/LICENSE.md
ecocycle-3.4.0.dist-info/METADATA
ecocycle-3.4.0.dist-info/WHEEL
ecocycle-3.4.0.dist-info/entry_points.txt
ecocycle-3.4.0.dist-info/top_level.txt
ecocycle-3.4.0.dist-info/RECORD
