Metadata-Version: 2.4
Name: ecocycle
Version: 3.4.0
Summary: EcoCycle - Sustainable Transportation Tracker and Route Planner
Home-page: https://github.com/shirishpothi/ecocycle
Author: Shirish Pothi
Author-email: shirish.pothi.27@gmail.com
Project-URL: Documentation, https://rebrand.ly/ecocycle
Project-URL: Source, https://github.com/shirishpothi/ecocycle
Project-URL: Tracker, https://github.com/shirishpothi/ecocycle/issues
Keywords: cycling sustainability eco-friendly route-planning carbon-footprint transportation
Classifier: Development Status :: 4 - Beta
Classifier: Environment :: Console
Classifier: Environment :: Web Environment
Classifier: Intended Audience :: End Users/Desktop
Classifier: Intended Audience :: Developers
Classifier: License :: OSI Approved :: Apache Software License
Classifier: Operating System :: OS Independent
Classifier: Programming Language :: Python :: 3
Classifier: Programming Language :: Python :: 3.11
Classifier: Programming Language :: Python :: 3.12
Classifier: Topic :: Scientific/Engineering :: GIS
Classifier: Topic :: Office/Business
Classifier: Topic :: Utilities
Classifier: Topic :: Internet :: WWW/HTTP :: Dynamic Content
Classifier: Topic :: Software Development :: Libraries :: Python Modules
Requires-Python: >=3.11
License-File: LICENSE.md
Requires-Dist: colorama>=0.4.6
Requires-Dist: python-dotenv>=1.0.1
Requires-Dist: tqdm>=4.66.1
Requires-Dist: rich>=14.0.0
Requires-Dist: termcolor>=2.3.0
Requires-Dist: blessed>=1.20.0
Requires-Dist: yaspin>=3.0.1
Requires-Dist: packaging>=23.0.0
Requires-Dist: setuptools>=78.1.0
Requires-Dist: requests>=2.32.3
Requires-Dist: cryptography>=44.0.1
Requires-Dist: bcrypt>=4.1.3
Requires-Dist: psutil>=5.9.0
Provides-Extra: visualization
Requires-Dist: matplotlib>=3.7.0; extra == "visualization"
Requires-Dist: numpy>=2.2.4; extra == "visualization"
Requires-Dist: plotly>=5.14.0; extra == "visualization"
Provides-Extra: route-planning
Requires-Dist: folium>=0.14.0; extra == "route-planning"
Requires-Dist: requests>=2.32.3; extra == "route-planning"
Provides-Extra: data-export
Requires-Dist: fpdf>=1.7.2; extra == "data-export"
Requires-Dist: tabulate>=0.9.0; extra == "data-export"
Provides-Extra: social-sharing
Requires-Dist: pillow>=10.0.0; extra == "social-sharing"
Requires-Dist: qrcode>=7.4.0; extra == "social-sharing"
Provides-Extra: notifications
Requires-Dist: sendgrid>=6.10.0; extra == "notifications"
Requires-Dist: twilio>=8.5.0; extra == "notifications"
Requires-Dist: yagmail>=0.15.293; extra == "notifications"
Provides-Extra: sheets-integration
Requires-Dist: google-api-python-client>=2.149.0; extra == "sheets-integration"
Requires-Dist: google-auth-httplib2>=0.2.0; extra == "sheets-integration"
Requires-Dist: google-auth-oauthlib>=1.0.0; extra == "sheets-integration"
Requires-Dist: google-auth>=2.35.0; extra == "sheets-integration"
Requires-Dist: oauthlib>=3.2.2; extra == "sheets-integration"
Provides-Extra: ai-features
Requires-Dist: openai>=1.74.0; extra == "ai-features"
Requires-Dist: google-generativeai>=0.8.4; extra == "ai-features"
Provides-Extra: weather
Requires-Dist: weatherapi>=0.0.4; extra == "weather"
Provides-Extra: web
Requires-Dist: flask>=3.1.0; extra == "web"
Requires-Dist: flask-cors>=5.0.0; extra == "web"
Requires-Dist: werkzeug>=3.0.0; extra == "web"
Requires-Dist: gunicorn>=21.0.0; extra == "web"
Requires-Dist: eventlet>=0.33.0; extra == "web"
Requires-Dist: flask-socketio>=5.3.0; extra == "web"
Provides-Extra: dev
Requires-Dist: pytest>=7.4.0; extra == "dev"
Requires-Dist: pytest-mock>=3.11.1; extra == "dev"
Requires-Dist: pytest-cov>=4.1.0; extra == "dev"
Requires-Dist: pytest-benchmark>=4.0.0; extra == "dev"
Requires-Dist: pytest-xdist>=3.5.0; extra == "dev"
Requires-Dist: black>=23.7.0; extra == "dev"
Requires-Dist: mypy>=1.5.1; extra == "dev"
Requires-Dist: flake8>=6.1.0; extra == "dev"
Requires-Dist: isort>=5.13.2; extra == "dev"
Requires-Dist: pre-commit>=3.6.0; extra == "dev"
Requires-Dist: bandit>=1.7.7; extra == "dev"
Requires-Dist: ruff>=0.1.6; extra == "dev"
Provides-Extra: all
Requires-Dist: matplotlib>=3.7.0; extra == "all"
Requires-Dist: numpy>=2.2.4; extra == "all"
Requires-Dist: plotly>=5.14.0; extra == "all"
Requires-Dist: folium>=0.14.0; extra == "all"
Requires-Dist: fpdf>=1.7.2; extra == "all"
Requires-Dist: tabulate>=0.9.0; extra == "all"
Requires-Dist: pillow>=10.0.0; extra == "all"
Requires-Dist: qrcode>=7.4.0; extra == "all"
Requires-Dist: sendgrid>=6.10.0; extra == "all"
Requires-Dist: twilio>=8.5.0; extra == "all"
Requires-Dist: yagmail>=0.15.293; extra == "all"
Requires-Dist: google-api-python-client>=2.149.0; extra == "all"
Requires-Dist: google-auth-httplib2>=0.2.0; extra == "all"
Requires-Dist: google-auth-oauthlib>=1.0.0; extra == "all"
Requires-Dist: google-auth>=2.35.0; extra == "all"
Requires-Dist: oauthlib>=3.2.2; extra == "all"
Requires-Dist: openai>=1.74.0; extra == "all"
Requires-Dist: google-generativeai>=0.8.4; extra == "all"
Requires-Dist: weatherapi>=0.0.4; extra == "all"
Requires-Dist: flask>=3.1.0; extra == "all"
Requires-Dist: flask-cors>=5.0.0; extra == "all"
Requires-Dist: werkzeug>=3.0.0; extra == "all"
Requires-Dist: gunicorn>=21.0.0; extra == "all"
Requires-Dist: eventlet>=0.33.0; extra == "all"
Requires-Dist: flask-socketio>=5.3.0; extra == "all"
Dynamic: author
Dynamic: author-email
Dynamic: classifier
Dynamic: description
Dynamic: description-content-type
Dynamic: home-page
Dynamic: keywords
Dynamic: license-file
Dynamic: project-url
Dynamic: provides-extra
Dynamic: requires-dist
Dynamic: requires-python
Dynamic: summary
